[
  {
    "timestamp": "2026-04-16T23:25:29.699001",
    "date": "2026-04-16",
    "stocks_processed": 68,
    "new_alerts": 0,
    "overbought": 62,
    "oversold": 0
  },
  {
    "timestamp": "2026-04-17T01:13:42.181922",
    "date": "2026-04-17",
    "stocks_processed": 68,
    "new_alerts": 48,
    "overbought": 48,
    "oversold": 0
  },
  {
    "timestamp": "2026-04-17T03:12:02.259361",
    "date": "2026-04-17",
    "stocks_processed": 68,
    "new_alerts": 1,
    "overbought": 49,
    "oversold": 0
  },
  {
    "timestamp": "2026-04-17T04:46:46.959778",
    "date": "2026-04-17",
    "stocks_processed": 68,
    "new_alerts": 0,
    "overbought": 49,
    "oversold": 0
  },
  {
    "timestamp": "2026-04-17T05:41:58.532256",
    "date": "2026-04-17",
    "stocks_processed": 68,
    "new_alerts": 0,
    "overbought": 49,
    "oversold": 0
  },
  {
    "timestamp": "2026-04-17T06:38:49.231815",
    "date": "2026-04-17",
    "stocks_processed": 68,
    "new_alerts": 0,
    "overbought": 49,
    "oversold": 0
  },
  {
    "timestamp": "2026-04-17T07:39:18.628802",
    "date": "2026-04-17",
    "stocks_processed": 68,
    "new_alerts": 0,
    "overbought": 49,
    "oversold": 0
  },
  {
    "timestamp": "2026-04-17T10:28:56.798463",
    "date": "2026-04-17",
    "stocks_processed": 68,
    "new_alerts": 13,
    "overbought": 62,
    "oversold": 0
  },
  {
    "timestamp": "2026-04-17T13:27:00.610797",
    "date": "2026-04-17",
    "stocks_processed": 68,
    "new_alerts": 0,
    "overbought": 61,
    "oversold": 0
  },
  {
    "timestamp": "2026-04-17T15:45:07.205719",
    "date": "2026-04-17",
    "stocks_processed": 68,
    "new_alerts": 0,
    "overbought": 61,
    "oversold": 0
  },
  {
    "timestamp": "2026-04-17T17:16:40.897313",
    "date": "2026-04-17",
    "stocks_processed": 68,
    "new_alerts": 0,
    "overbought": 61,
    "oversold": 0
  },
  {
    "timestamp": "2026-04-17T18:55:10.275089",
    "date": "2026-04-17",
    "stocks_processed": 68,
    "new_alerts": 0,
    "overbought": 61,
    "oversold": 0
  },
  {
    "timestamp": "2026-04-17T19:52:15.256878",
    "date": "2026-04-17",
    "stocks_processed": 68,
    "new_alerts": 0,
    "overbought": 61,
    "oversold": 0
  },
  {
    "timestamp": "2026-04-17T21:17:25.772510",
    "date": "2026-04-17",
    "stocks_processed": 68,
    "new_alerts": 0,
    "overbought": 61,
    "oversold": 0
  },
  {
    "timestamp": "2026-04-17T22:54:51.006429",
    "date": "2026-04-17",
    "stocks_processed": 68,
    "new_alerts": 0,
    "overbought": 60,
    "oversold": 0
  },
  {
    "timestamp": "2026-04-18T00:00:10.744364",
    "date": "2026-04-18",
    "stocks_processed": 68,
    "new_alerts": 60,
    "overbought": 60,
    "oversold": 0
  },
  {
    "timestamp": "2026-04-18T01:03:03.005054",
    "date": "2026-04-18",
    "stocks_processed": 68,
    "new_alerts": 0,
    "overbought": 54,
    "oversold": 0
  },
  {
    "timestamp": "2026-04-18T02:59:18.134208",
    "date": "2026-04-18",
    "stocks_processed": 68,
    "new_alerts": 0,
    "overbought": 55,
    "oversold": 0
  },
  {
    "timestamp": "2026-04-18T04:00:49.384636",
    "date": "2026-04-18",
    "stocks_processed": 68,
    "new_alerts": 0,
    "overbought": 55,
    "oversold": 0
  },
  {
    "timestamp": "2026-04-18T05:40:36.005585",
    "date": "2026-04-18",
    "stocks_processed": 68,
    "new_alerts": 0,
    "overbought": 55,
    "oversold": 0
  },
  {
    "timestamp": "2026-04-18T06:38:00.376898",
    "date": "2026-04-18",
    "stocks_processed": 68,
    "new_alerts": 0,
    "overbought": 55,
    "oversold": 0
  },
  {
    "timestamp": "2026-04-18T07:38:19.535087",
    "date": "2026-04-18",
    "stocks_processed": 68,
    "new_alerts": 0,
    "overbought": 55,
    "oversold": 0
  },
  {
    "timestamp": "2026-04-18T10:11:56.457129",
    "date": "2026-04-18",
    "stocks_processed": 68,
    "new_alerts": 0,
    "overbought": 55,
    "oversold": 0
  },
  {
    "timestamp": "2026-04-18T13:05:55.271125",
    "date": "2026-04-18",
    "stocks_processed": 68,
    "new_alerts": 0,
    "overbought": 60,
    "oversold": 0
  },
  {
    "timestamp": "2026-04-18T15:05:54.546959",
    "date": "2026-04-18",
    "stocks_processed": 68,
    "new_alerts": 0,
    "overbought": 60,
    "oversold": 0
  },
  {
    "timestamp": "2026-04-18T16:49:33.626092",
    "date": "2026-04-18",
    "stocks_processed": 68,
    "new_alerts": 0,
    "overbought": 60,
    "oversold": 0
  },
  {
    "timestamp": "2026-04-18T17:47:02.517951",
    "date": "2026-04-18",
    "stocks_processed": 68,
    "new_alerts": 0,
    "overbought": 60,
    "oversold": 0
  },
  {
    "timestamp": "2026-04-18T18:39:12.069291",
    "date": "2026-04-18",
    "stocks_processed": 68,
    "new_alerts": 0,
    "overbought": 60,
    "oversold": 0
  },
  {
    "timestamp": "2026-04-18T19:34:06.532093",
    "date": "2026-04-18",
    "stocks_processed": 68,
    "new_alerts": 0,
    "overbought": 60,
    "oversold": 0
  },
  {
    "timestamp": "2026-04-18T20:59:59.667686",
    "date": "2026-04-18",
    "stocks_processed": 68,
    "new_alerts": 0,
    "overbought": 60,
    "oversold": 0
  }
]