[
  {
    "timestamp": "2026-07-15T02:01:31.150910",
    "date": "2026-07-15",
    "stocks_processed": 125,
    "new_alerts": 2,
    "overbought": 15,
    "oversold": 17
  },
  {
    "timestamp": "2026-07-15T04:09:42.854129",
    "date": "2026-07-15",
    "stocks_processed": 125,
    "new_alerts": 0,
    "overbought": 15,
    "oversold": 17
  },
  {
    "timestamp": "2026-07-15T05:56:57.641387",
    "date": "2026-07-15",
    "stocks_processed": 125,
    "new_alerts": 0,
    "overbought": 15,
    "oversold": 17
  },
  {
    "timestamp": "2026-07-15T06:56:32.308984",
    "date": "2026-07-15",
    "stocks_processed": 125,
    "new_alerts": 0,
    "overbought": 15,
    "oversold": 17
  },
  {
    "timestamp": "2026-07-15T07:53:21.413473",
    "date": "2026-07-15",
    "stocks_processed": 125,
    "new_alerts": 0,
    "overbought": 15,
    "oversold": 17
  },
  {
    "timestamp": "2026-07-15T10:14:38.083333",
    "date": "2026-07-15",
    "stocks_processed": 125,
    "new_alerts": 1,
    "overbought": 15,
    "oversold": 17
  },
  {
    "timestamp": "2026-07-15T13:29:46.935458",
    "date": "2026-07-15",
    "stocks_processed": 125,
    "new_alerts": 0,
    "overbought": 15,
    "oversold": 13
  },
  {
    "timestamp": "2026-07-15T16:06:50.861576",
    "date": "2026-07-15",
    "stocks_processed": 125,
    "new_alerts": 0,
    "overbought": 15,
    "oversold": 15
  },
  {
    "timestamp": "2026-07-15T18:48:41.040117",
    "date": "2026-07-15",
    "stocks_processed": 125,
    "new_alerts": 0,
    "overbought": 15,
    "oversold": 15
  },
  {
    "timestamp": "2026-07-15T20:15:03.289480",
    "date": "2026-07-15",
    "stocks_processed": 125,
    "new_alerts": 0,
    "overbought": 15,
    "oversold": 15
  },
  {
    "timestamp": "2026-07-15T22:49:02.075212",
    "date": "2026-07-15",
    "stocks_processed": 125,
    "new_alerts": 1,
    "overbought": 16,
    "oversold": 15
  },
  {
    "timestamp": "2026-07-16T00:20:58.445672",
    "date": "2026-07-16",
    "stocks_processed": 125,
    "new_alerts": 34,
    "overbought": 16,
    "oversold": 18
  },
  {
    "timestamp": "2026-07-16T02:06:09.302002",
    "date": "2026-07-16",
    "stocks_processed": 125,
    "new_alerts": 2,
    "overbought": 17,
    "oversold": 15
  },
  {
    "timestamp": "2026-07-16T04:08:27.333222",
    "date": "2026-07-16",
    "stocks_processed": 125,
    "new_alerts": 1,
    "overbought": 19,
    "oversold": 16
  },
  {
    "timestamp": "2026-07-16T06:00:05.161571",
    "date": "2026-07-16",
    "stocks_processed": 125,
    "new_alerts": 0,
    "overbought": 19,
    "oversold": 16
  },
  {
    "timestamp": "2026-07-16T07:03:32.833954",
    "date": "2026-07-16",
    "stocks_processed": 125,
    "new_alerts": 0,
    "overbought": 19,
    "oversold": 16
  },
  {
    "timestamp": "2026-07-16T10:27:05.434160",
    "date": "2026-07-16",
    "stocks_processed": 125,
    "new_alerts": 2,
    "overbought": 20,
    "oversold": 16
  },
  {
    "timestamp": "2026-07-16T13:40:08.299292",
    "date": "2026-07-16",
    "stocks_processed": 125,
    "new_alerts": 1,
    "overbought": 21,
    "oversold": 13
  },
  {
    "timestamp": "2026-07-16T16:09:47.700880",
    "date": "2026-07-16",
    "stocks_processed": 125,
    "new_alerts": 0,
    "overbought": 21,
    "oversold": 13
  },
  {
    "timestamp": "2026-07-16T18:58:29.826514",
    "date": "2026-07-16",
    "stocks_processed": 125,
    "new_alerts": 0,
    "overbought": 21,
    "oversold": 13
  },
  {
    "timestamp": "2026-07-16T20:23:18.393199",
    "date": "2026-07-16",
    "stocks_processed": 125,
    "new_alerts": 0,
    "overbought": 21,
    "oversold": 13
  },
  {
    "timestamp": "2026-07-16T23:00:21.226335",
    "date": "2026-07-16",
    "stocks_processed": 125,
    "new_alerts": 2,
    "overbought": 20,
    "oversold": 15
  },
  {
    "timestamp": "2026-07-17T00:25:30.285439",
    "date": "2026-07-17",
    "stocks_processed": 125,
    "new_alerts": 38,
    "overbought": 21,
    "oversold": 17
  },
  {
    "timestamp": "2026-07-17T02:05:53.067238",
    "date": "2026-07-17",
    "stocks_processed": 125,
    "new_alerts": 0,
    "overbought": 19,
    "oversold": 17
  },
  {
    "timestamp": "2026-07-17T04:02:58.170644",
    "date": "2026-07-17",
    "stocks_processed": 125,
    "new_alerts": 1,
    "overbought": 16,
    "oversold": 17
  },
  {
    "timestamp": "2026-07-17T06:02:53.440740",
    "date": "2026-07-17",
    "stocks_processed": 125,
    "new_alerts": 0,
    "overbought": 16,
    "oversold": 17
  },
  {
    "timestamp": "2026-07-17T07:58:46.393236",
    "date": "2026-07-17",
    "stocks_processed": 125,
    "new_alerts": 0,
    "overbought": 16,
    "oversold": 17
  },
  {
    "timestamp": "2026-07-17T10:55:38.333452",
    "date": "2026-07-17",
    "stocks_processed": 125,
    "new_alerts": 11,
    "overbought": 12,
    "oversold": 28
  },
  {
    "timestamp": "2026-07-17T13:42:42.430782",
    "date": "2026-07-17",
    "stocks_processed": 125,
    "new_alerts": 0,
    "overbought": 11,
    "oversold": 28
  },
  {
    "timestamp": "2026-07-17T16:08:16.978663",
    "date": "2026-07-17",
    "stocks_processed": 125,
    "new_alerts": 0,
    "overbought": 10,
    "oversold": 28
  }
]