[
  {
    "timestamp": "2026-05-28T05:53:11.739240",
    "date": "2026-05-28",
    "stocks_processed": 96,
    "new_alerts": 0,
    "overbought": 35,
    "oversold": 6
  },
  {
    "timestamp": "2026-05-28T07:16:18.912368",
    "date": "2026-05-28",
    "stocks_processed": 96,
    "new_alerts": 0,
    "overbought": 35,
    "oversold": 6
  },
  {
    "timestamp": "2026-05-28T10:58:14.626804",
    "date": "2026-05-28",
    "stocks_processed": 96,
    "new_alerts": 10,
    "overbought": 43,
    "oversold": 7
  },
  {
    "timestamp": "2026-05-28T14:58:26.225211",
    "date": "2026-05-28",
    "stocks_processed": 96,
    "new_alerts": 0,
    "overbought": 26,
    "oversold": 7
  },
  {
    "timestamp": "2026-05-28T18:59:38.117775",
    "date": "2026-05-28",
    "stocks_processed": 96,
    "new_alerts": 0,
    "overbought": 26,
    "oversold": 7
  },
  {
    "timestamp": "2026-05-28T22:43:35.980264",
    "date": "2026-05-28",
    "stocks_processed": 96,
    "new_alerts": 5,
    "overbought": 34,
    "oversold": 8
  },
  {
    "timestamp": "2026-05-29T02:11:27.478746",
    "date": "2026-05-29",
    "stocks_processed": 96,
    "new_alerts": 40,
    "overbought": 35,
    "oversold": 5
  },
  {
    "timestamp": "2026-05-29T05:08:06.486465",
    "date": "2026-05-29",
    "stocks_processed": 96,
    "new_alerts": 0,
    "overbought": 35,
    "oversold": 5
  },
  {
    "timestamp": "2026-05-29T07:15:24.795787",
    "date": "2026-05-29",
    "stocks_processed": 96,
    "new_alerts": 0,
    "overbought": 35,
    "oversold": 5
  },
  {
    "timestamp": "2026-05-29T11:27:20.629289",
    "date": "2026-05-29",
    "stocks_processed": 96,
    "new_alerts": 15,
    "overbought": 49,
    "oversold": 4
  },
  {
    "timestamp": "2026-05-29T15:54:40.356122",
    "date": "2026-05-29",
    "stocks_processed": 96,
    "new_alerts": 1,
    "overbought": 50,
    "oversold": 4
  },
  {
    "timestamp": "2026-05-29T19:28:12.460769",
    "date": "2026-05-29",
    "stocks_processed": 96,
    "new_alerts": 0,
    "overbought": 50,
    "oversold": 4
  },
  {
    "timestamp": "2026-05-29T23:24:28.833804",
    "date": "2026-05-29",
    "stocks_processed": 96,
    "new_alerts": 4,
    "overbought": 54,
    "oversold": 4
  },
  {
    "timestamp": "2026-05-30T02:31:32.462208",
    "date": "2026-05-30",
    "stocks_processed": 96,
    "new_alerts": 56,
    "overbought": 51,
    "oversold": 5
  },
  {
    "timestamp": "2026-05-30T05:06:44.205584",
    "date": "2026-05-30",
    "stocks_processed": 96,
    "new_alerts": 4,
    "overbought": 52,
    "oversold": 8
  },
  {
    "timestamp": "2026-05-30T07:11:27.264254",
    "date": "2026-05-30",
    "stocks_processed": 96,
    "new_alerts": 0,
    "overbought": 52,
    "oversold": 8
  },
  {
    "timestamp": "2026-05-30T10:54:34.358472",
    "date": "2026-05-30",
    "stocks_processed": 96,
    "new_alerts": 0,
    "overbought": 52,
    "oversold": 8
  },
  {
    "timestamp": "2026-05-30T14:23:29.813314",
    "date": "2026-05-30",
    "stocks_processed": 96,
    "new_alerts": 0,
    "overbought": 52,
    "oversold": 8
  },
  {
    "timestamp": "2026-05-30T17:14:38.028205",
    "date": "2026-05-30",
    "stocks_processed": 96,
    "new_alerts": 0,
    "overbought": 52,
    "oversold": 8
  },
  {
    "timestamp": "2026-05-30T19:19:15.978334",
    "date": "2026-05-30",
    "stocks_processed": 96,
    "new_alerts": 0,
    "overbought": 52,
    "oversold": 8
  },
  {
    "timestamp": "2026-05-30T21:26:17.010808",
    "date": "2026-05-30",
    "stocks_processed": 96,
    "new_alerts": 0,
    "overbought": 52,
    "oversold": 8
  },
  {
    "timestamp": "2026-05-30T23:05:48.078078",
    "date": "2026-05-30",
    "stocks_processed": 96,
    "new_alerts": 0,
    "overbought": 52,
    "oversold": 8
  },
  {
    "timestamp": "2026-05-31T01:02:44.254450",
    "date": "2026-05-31",
    "stocks_processed": 96,
    "new_alerts": 60,
    "overbought": 52,
    "oversold": 8
  },
  {
    "timestamp": "2026-05-31T03:12:39.233078",
    "date": "2026-05-31",
    "stocks_processed": 96,
    "new_alerts": 0,
    "overbought": 52,
    "oversold": 8
  },
  {
    "timestamp": "2026-05-31T04:55:11.830066",
    "date": "2026-05-31",
    "stocks_processed": 96,
    "new_alerts": 0,
    "overbought": 52,
    "oversold": 8
  },
  {
    "timestamp": "2026-05-31T06:00:58.631834",
    "date": "2026-05-31",
    "stocks_processed": 96,
    "new_alerts": 0,
    "overbought": 52,
    "oversold": 8
  },
  {
    "timestamp": "2026-05-31T07:09:25.064750",
    "date": "2026-05-31",
    "stocks_processed": 96,
    "new_alerts": 0,
    "overbought": 52,
    "oversold": 8
  },
  {
    "timestamp": "2026-05-31T11:40:19.670488",
    "date": "2026-05-31",
    "stocks_processed": 96,
    "new_alerts": 0,
    "overbought": 52,
    "oversold": 8
  },
  {
    "timestamp": "2026-05-31T15:44:45.364725",
    "date": "2026-05-31",
    "stocks_processed": 96,
    "new_alerts": 0,
    "overbought": 52,
    "oversold": 8
  },
  {
    "timestamp": "2026-05-31T18:15:39.392645",
    "date": "2026-05-31",
    "stocks_processed": 96,
    "new_alerts": 0,
    "overbought": 52,
    "oversold": 8
  }
]