{
  "timestamp": "2026-06-26T18:50:27.901829",
  "date": "2026-06-26",
  "macro": {
    "us10y": {
      "value": 4.392,
      "change": 0.0
    },
    "dxy": {
      "value": 101.2,
      "change": -0.23
    },
    "fear_greed": {
      "value": 20.17,
      "change": 1.28,
      "label": "VIX Index",
      "timestamp": "2026-06-26T18:50:21.883866"
    },
    "btc": {
      "value": 59375.0,
      "change_pct": -0.58
    }
  },
  "stocks_processed": 125,
  "stocks_successful": 125,
  "stocks_failed": 0,
  "new_alerts": 0,
  "overbought_count": 4,
  "oversold_count": 27,
  "normal_count": 94,
  "overbought_stocks": [
    {
      "symbol": "00652.TW",
      "name": "富邦印度",
      "current_price": 33.04,
      "change_pct": -0.9,
      "extra_data": {
        "regular_market_price": 33.04,
        "pre_market_price": null,
        "post_market_price": null,
        "prev_close": 33.34
      },
      "kd_k": 85.57,
      "kd_d": 85.97
    },
    {
      "symbol": "00653L.TW",
      "name": "富邦印度正2",
      "current_price": 46.02,
      "change_pct": -2.11,
      "extra_data": {
        "regular_market_price": 46.02,
        "pre_market_price": null,
        "post_market_price": null,
        "prev_close": 47.01
      },
      "kd_k": 74.49,
      "kd_d": 81.34
    },
    {
      "symbol": "00731.TW",
      "name": "復華富時高息低波",
      "current_price": 88.55,
      "change_pct": -2.64,
      "extra_data": {
        "regular_market_price": 88.55,
        "pre_market_price": null,
        "post_market_price": null,
        "prev_close": 90.95
      },
      "kd_k": 65.79,
      "kd_d": 80.2
    },
    {
      "symbol": "00915.TW",
      "name": "凱基優選高股息30",
      "current_price": 32.01,
      "change_pct": -3.82,
      "extra_data": {
        "regular_market_price": 32.01,
        "pre_market_price": null,
        "post_market_price": null,
        "prev_close": 33.28
      },
      "kd_k": 72.02,
      "kd_d": 82.75
    }
  ],
  "oversold_stocks": [
    {
      "symbol": "00635U.TW",
      "name": "期元大S&P黃金",
      "current_price": 41.9,
      "change_pct": 0.58,
      "extra_data": {
        "regular_market_price": 41.9,
        "pre_market_price": null,
        "post_market_price": null,
        "prev_close": 41.66
      },
      "kd_k": 19.66,
      "kd_d": 30.76
    },
    {
      "symbol": "00665L.TW",
      "name": "富邦恒生國企正2",
      "current_price": 7.38,
      "change_pct": -3.02,
      "extra_data": {
        "regular_market_price": 7.38,
        "pre_market_price": null,
        "post_market_price": null,
        "prev_close": 7.61
      },
      "kd_k": 5.57,
      "kd_d": 9.18
    },
    {
      "symbol": "00708L.TW",
      "name": "期元大S&P黃金正2",
      "current_price": 69.65,
      "change_pct": 1.09,
      "extra_data": {
        "regular_market_price": 69.65,
        "pre_market_price": null,
        "post_market_price": null,
        "prev_close": 68.9
      },
      "kd_k": 19.34,
      "kd_d": 29.53
    },
    {
      "symbol": "00715L.TW",
      "name": "期街口布蘭特正2",
      "current_price": 34.27,
      "change_pct": 3.32,
      "extra_data": {
        "regular_market_price": 34.27,
        "pre_market_price": null,
        "post_market_price": null,
        "prev_close": 33.17
      },
      "kd_k": 6.01,
      "kd_d": 5.93
    },
    {
      "symbol": "00753L.TW",
      "name": "中信中國50正2",
      "current_price": 7.96,
      "change_pct": -4.1,
      "extra_data": {
        "regular_market_price": 7.96,
        "pre_market_price": null,
        "post_market_price": null,
        "prev_close": 8.3
      },
      "kd_k": 7.55,
      "kd_d": 12.14
    },
    {
      "symbol": "00910.TW",
      "name": "第一金太空衛星",
      "current_price": 57.35,
      "change_pct": -4.34,
      "extra_data": {
        "regular_market_price": 57.35,
        "pre_market_price": null,
        "post_market_price": null,
        "prev_close": 59.95
      },
      "kd_k": 3.47,
      "kd_d": 7.73
    },
    {
      "symbol": "00955.TWO",
      "name": "中信日本商社",
      "current_price": 13.84,
      "change_pct": 0.36,
      "extra_data": {
        "regular_market_price": 13.84,
        "pre_market_price": null,
        "post_market_price": null,
        "prev_close": 13.79
      },
      "kd_k": 11.76,
      "kd_d": 19.53
    },
    {
      "symbol": "2317.TW",
      "name": "鴻海",
      "current_price": 248.5,
      "change_pct": -3.5,
      "extra_data": {
        "regular_market_price": 248.5,
        "pre_market_price": null,
        "post_market_price": null,
        "prev_close": 257.5
      },
      "kd_k": 19.54,
      "kd_d": 30.84
    },
    {
      "symbol": "MSFT",
      "name": "Microsoft Corp.",
      "current_price": 352.83,
      "change_pct": -3.45,
      "extra_data": {
        "regular_market_price": 352.83,
        "pre_market_price": 356.3644,
        "post_market_price": null,
        "prev_close": 365.445
      },
      "kd_k": 8.17,
      "kd_d": 10.59
    },
    {
      "symbol": "AMZN",
      "name": "Amazon.com Inc.",
      "current_price": 227.01,
      "change_pct": -3.14,
      "extra_data": {
        "regular_market_price": 227.01,
        "pre_market_price": 227.38,
        "post_market_price": null,
        "prev_close": 234.37
      },
      "kd_k": 15.18,
      "kd_d": 21.98
    },
    {
      "symbol": "META",
      "name": "Meta Platforms Inc.",
      "current_price": 542.87,
      "change_pct": -2.68,
      "extra_data": {
        "regular_market_price": 542.87,
        "pre_market_price": 544.7,
        "post_market_price": null,
        "prev_close": 557.8
      },
      "kd_k": 11.79,
      "kd_d": 18.65
    },
    {
      "symbol": "NFLX",
      "name": "Netflix Inc.",
      "current_price": 70.9,
      "change_pct": -1.32,
      "extra_data": {
        "regular_market_price": 70.9,
        "pre_market_price": 71.45,
        "post_market_price": null,
        "prev_close": 71.845
      },
      "kd_k": 6.36,
      "kd_d": 11.31
    },
    {
      "symbol": "PLTR",
      "name": "Palantir Technologies Inc.",
      "current_price": 107.27,
      "change_pct": -5.5,
      "extra_data": {
        "regular_market_price": 107.27,
        "pre_market_price": 108.8715,
        "post_market_price": null,
        "prev_close": 113.51
      },
      "kd_k": 7.74,
      "kd_d": 13.08
    },
    {
      "symbol": "AMZU",
      "name": "Direxion Daily AMZN Bull 2X Shares",
      "current_price": 30.33,
      "change_pct": -6.16,
      "extra_data": {
        "regular_market_price": 30.33,
        "pre_market_price": 30.36,
        "post_market_price": null,
        "prev_close": 32.32
      },
      "kd_k": 13.94,
      "kd_d": 19.59
    },
    {
      "symbol": "MSFU",
      "name": "Direxion Daily MSFT Bull 2X Shares",
      "current_price": 19.88,
      "change_pct": -6.97,
      "extra_data": {
        "regular_market_price": 19.88,
        "pre_market_price": 20.28,
        "post_market_price": null,
        "prev_close": 21.37
      },
      "kd_k": 7.24,
      "kd_d": 9.37
    },
    {
      "symbol": "FBL",
      "name": "GraniteShares 2x Long META Daily ETF",
      "current_price": 19.49,
      "change_pct": -5.39,
      "extra_data": {
        "regular_market_price": 19.49,
        "pre_market_price": 19.62,
        "post_market_price": null,
        "prev_close": 20.6
      },
      "kd_k": 9.37,
      "kd_d": 15.54
    },
    {
      "symbol": "NFXL",
      "name": "Direxion Daily NFLX Bull 2X Shares",
      "current_price": 15.44,
      "change_pct": -2.71,
      "extra_data": {
        "regular_market_price": 15.44,
        "pre_market_price": 15.61,
        "post_market_price": null,
        "prev_close": 15.87
      },
      "kd_k": 5.74,
      "kd_d": 10.42
    },
    {
      "symbol": "CRCL",
      "name": "Circle Internet Group, Inc.",
      "current_price": 68.81,
      "change_pct": -3.06,
      "extra_data": {
        "regular_market_price": 68.81,
        "pre_market_price": 68.2224,
        "post_market_price": null,
        "prev_close": 70.98
      },
      "kd_k": 11.95,
      "kd_d": 15.94
    },
    {
      "symbol": "CRM",
      "name": "Salesforce, Inc.",
      "current_price": 150.19,
      "change_pct": -1.68,
      "extra_data": {
        "regular_market_price": 150.19,
        "pre_market_price": 151.84,
        "post_market_price": null,
        "prev_close": 152.76
      },
      "kd_k": 17.52,
      "kd_d": 14.89
    },
    {
      "symbol": "CRMG",
      "name": "Leverage Shares 2X Long CRM Daily ETF",
      "current_price": 3.78,
      "change_pct": -3.08,
      "extra_data": {
        "regular_market_price": 3.78,
        "pre_market_price": 3.83,
        "post_market_price": null,
        "prev_close": 3.9
      },
      "kd_k": 12.8,
      "kd_d": 11.56
    },
    {
      "symbol": "ADBE",
      "name": "Adobe Inc.",
      "current_price": 193.41,
      "change_pct": -1.6,
      "extra_data": {
        "regular_market_price": 193.41,
        "pre_market_price": 195.5,
        "post_market_price": null,
        "prev_close": 196.55
      },
      "kd_k": 13.35,
      "kd_d": 12.44
    },
    {
      "symbol": "ADBG",
      "name": "Leverage Shares 2X Long ADBE Daily ETF",
      "current_price": 2.67,
      "change_pct": -3.61,
      "extra_data": {
        "regular_market_price": 2.67,
        "pre_market_price": 2.72,
        "post_market_price": null,
        "prev_close": 2.77
      },
      "kd_k": 10.44,
      "kd_d": 10.09
    },
    {
      "symbol": "ORCL",
      "name": "Oracle Corporation",
      "current_price": 152.46,
      "change_pct": -3.22,
      "extra_data": {
        "regular_market_price": 152.46,
        "pre_market_price": 150.01,
        "post_market_price": null,
        "prev_close": 157.53
      },
      "kd_k": 6.98,
      "kd_d": 11.54
    },
    {
      "symbol": "ORCX",
      "name": "Defiance Daily Target 2X Long ORCL ETF",
      "current_price": 25.24,
      "change_pct": -6.17,
      "extra_data": {
        "regular_market_price": 25.24,
        "pre_market_price": 24.35,
        "post_market_price": null,
        "prev_close": 26.9
      },
      "kd_k": 6.43,
      "kd_d": 10.37
    },
    {
      "symbol": "TSLL",
      "name": "Direxion Daily TSLA Bull 2X Shares",
      "current_price": 11.38,
      "change_pct": -0.31,
      "extra_data": {
        "regular_market_price": 11.38,
        "pre_market_price": 11.112,
        "post_market_price": null,
        "prev_close": 11.415
      },
      "kd_k": 17.96,
      "kd_d": 27.05
    },
    {
      "symbol": "RKLB",
      "name": "Rocket Lab USA, Inc.",
      "current_price": 80.69,
      "change_pct": -5.53,
      "extra_data": {
        "regular_market_price": 80.69,
        "pre_market_price": 82.04,
        "post_market_price": null,
        "prev_close": 85.41
      },
      "kd_k": 9.22,
      "kd_d": 16.97
    },
    {
      "symbol": "RKLX",
      "name": "Defiance Daily Target 2X Long RKLB ETF",
      "current_price": 28.87,
      "change_pct": -11.09,
      "extra_data": {
        "regular_market_price": 28.87,
        "pre_market_price": 29.73,
        "post_market_price": null,
        "prev_close": 32.47
      },
      "kd_k": 7.64,
      "kd_d": 13.96
    }
  ],
  "errors": []
}