{
  "timestamp": "2026-07-06T20:45:53.636265",
  "date": "2026-07-06",
  "macro": {
    "us10y": {
      "value": 4.461,
      "change": -0.024
    },
    "dxy": {
      "value": 101.09,
      "change": 0.0
    },
    "fear_greed": {
      "value": 16.41,
      "change": 0.0,
      "label": "VIX Index",
      "timestamp": "2026-07-06T20:45:47.751314"
    },
    "btc": {
      "value": 61746.0,
      "change_pct": -2.83
    }
  },
  "stocks_processed": 125,
  "stocks_successful": 125,
  "stocks_failed": 0,
  "new_alerts": 0,
  "overbought_count": 8,
  "oversold_count": 16,
  "normal_count": 101,
  "overbought_stocks": [
    {
      "symbol": "00646.TW",
      "name": "元大S&P500",
      "current_price": 75.65,
      "change_pct": 0.6,
      "extra_data": {
        "regular_market_price": 75.65,
        "pre_market_price": null,
        "post_market_price": null,
        "prev_close": 75.2
      },
      "kd_k": 90.54,
      "kd_d": 79.89
    },
    {
      "symbol": "00647L.TW",
      "name": "元大S&P500正2",
      "current_price": 134.7,
      "change_pct": 0.15,
      "extra_data": {
        "regular_market_price": 134.7,
        "pre_market_price": null,
        "post_market_price": null,
        "prev_close": 134.5
      },
      "kd_k": 87.0,
      "kd_d": 72.38
    },
    {
      "symbol": "00652.TW",
      "name": "富邦印度",
      "current_price": 33.65,
      "change_pct": 0.51,
      "extra_data": {
        "regular_market_price": 33.65,
        "pre_market_price": null,
        "post_market_price": null,
        "prev_close": 33.48
      },
      "kd_k": 89.31,
      "kd_d": 84.72
    },
    {
      "symbol": "00653L.TW",
      "name": "富邦印度正2",
      "current_price": 48.07,
      "change_pct": 0.61,
      "extra_data": {
        "regular_market_price": 48.07,
        "pre_market_price": null,
        "post_market_price": null,
        "prev_close": 47.78
      },
      "kd_k": 85.94,
      "kd_d": 77.59
    },
    {
      "symbol": "00757.TW",
      "name": "統一FANG+",
      "current_price": 129.8,
      "change_pct": 0.54,
      "extra_data": {
        "regular_market_price": 129.8,
        "pre_market_price": null,
        "post_market_price": null,
        "prev_close": 129.1
      },
      "kd_k": 80.74,
      "kd_d": 64.67
    },
    {
      "symbol": "00852L.TW",
      "name": "國泰美國道瓊正2",
      "current_price": 35.54,
      "change_pct": -0.22,
      "extra_data": {
        "regular_market_price": 35.54,
        "pre_market_price": null,
        "post_market_price": null,
        "prev_close": 35.62
      },
      "kd_k": 92.77,
      "kd_d": 90.89
    },
    {
      "symbol": "00858.TWO",
      "name": "永豐美國500大",
      "current_price": 36.66,
      "change_pct": 0.44,
      "extra_data": {
        "regular_market_price": 36.66,
        "pre_market_price": null,
        "post_market_price": null,
        "prev_close": 36.5
      },
      "kd_k": 91.0,
      "kd_d": 81.06
    },
    {
      "symbol": "00924.TW",
      "name": "復華 S&P 500 成長",
      "current_price": 32.58,
      "change_pct": 0.43,
      "extra_data": {
        "regular_market_price": 32.58,
        "pre_market_price": null,
        "post_market_price": null,
        "prev_close": 32.44
      },
      "kd_k": 87.28,
      "kd_d": 75.22
    }
  ],
  "oversold_stocks": [
    {
      "symbol": "00715L.TW",
      "name": "期街口布蘭特正2",
      "current_price": 32.48,
      "change_pct": -0.37,
      "extra_data": {
        "regular_market_price": 32.48,
        "pre_market_price": null,
        "post_market_price": null,
        "prev_close": 32.6
      },
      "kd_k": 15.38,
      "kd_d": 10.44
    },
    {
      "symbol": "00909.TW",
      "name": "國泰數位支付服務",
      "current_price": 46.18,
      "change_pct": 0.11,
      "extra_data": {
        "regular_market_price": 46.18,
        "pre_market_price": null,
        "post_market_price": null,
        "prev_close": 46.13
      },
      "kd_k": 16.88,
      "kd_d": 27.19
    },
    {
      "symbol": "009819.TW",
      "name": "中信數據及電力",
      "current_price": 10.08,
      "change_pct": -0.2,
      "extra_data": {
        "regular_market_price": 10.08,
        "pre_market_price": null,
        "post_market_price": null,
        "prev_close": 10.1
      },
      "kd_k": 14.54,
      "kd_d": 19.69
    },
    {
      "symbol": "2317.TW",
      "name": "鴻海",
      "current_price": 242.0,
      "change_pct": 0.62,
      "extra_data": {
        "regular_market_price": 242.0,
        "pre_market_price": null,
        "post_market_price": null,
        "prev_close": 240.5
      },
      "kd_k": 16.76,
      "kd_d": 13.46
    },
    {
      "symbol": "AVGO",
      "name": "Broadcom Inc.",
      "current_price": 360.45,
      "change_pct": -2.41,
      "extra_data": {
        "regular_market_price": 360.45,
        "pre_market_price": 373.8,
        "post_market_price": null,
        "prev_close": 369.34003
      },
      "kd_k": 16.8,
      "kd_d": 21.97
    },
    {
      "symbol": "CRWD",
      "name": "CrowdStrike Holdings Inc.",
      "current_price": 193.98,
      "change_pct": 0.41,
      "extra_data": {
        "regular_market_price": 193.98,
        "pre_market_price": 191.721,
        "post_market_price": null,
        "prev_close": 193.185
      },
      "kd_k": 7.4,
      "kd_d": 14.37
    },
    {
      "symbol": "NVDL",
      "name": "GraniteShares 2x Long NVDA Daily ETF",
      "current_price": 28.22,
      "change_pct": -3.16,
      "extra_data": {
        "regular_market_price": 28.22,
        "pre_market_price": 28.369,
        "post_market_price": null,
        "prev_close": 29.14
      },
      "kd_k": 8.39,
      "kd_d": 7.76
    },
    {
      "symbol": "MULL",
      "name": "GraniteShares 2x Long MU Daily ETF",
      "current_price": 25.79,
      "change_pct": -11.74,
      "extra_data": {
        "regular_market_price": 25.79,
        "pre_market_price": 27.5704,
        "post_market_price": null,
        "prev_close": 29.220001
      },
      "kd_k": 4.7,
      "kd_d": 8.52
    },
    {
      "symbol": "AVGX",
      "name": "Defiance Daily Target 2X Long AVGO ETF",
      "current_price": 42.2,
      "change_pct": -5.32,
      "extra_data": {
        "regular_market_price": 42.2,
        "pre_market_price": 45.55,
        "post_market_price": null,
        "prev_close": 44.57
      },
      "kd_k": 13.92,
      "kd_d": 18.93
    },
    {
      "symbol": "CRCL",
      "name": "Circle Internet Group, Inc.",
      "current_price": 64.62,
      "change_pct": 4.31,
      "extra_data": {
        "regular_market_price": 64.62,
        "pre_market_price": 64.6321,
        "post_market_price": null,
        "prev_close": 61.95
      },
      "kd_k": 12.72,
      "kd_d": 16.02
    },
    {
      "symbol": "ORCL",
      "name": "Oracle Corporation",
      "current_price": 140.27,
      "change_pct": -1.56,
      "extra_data": {
        "regular_market_price": 140.27,
        "pre_market_price": 144.11,
        "post_market_price": null,
        "prev_close": 142.5
      },
      "kd_k": 3.22,
      "kd_d": 4.87
    },
    {
      "symbol": "ORCX",
      "name": "Defiance Daily Target 2X Long ORCL ETF",
      "current_price": 21.15,
      "change_pct": -3.6,
      "extra_data": {
        "regular_market_price": 21.15,
        "pre_market_price": 22.3,
        "post_market_price": null,
        "prev_close": 21.94
      },
      "kd_k": 2.85,
      "kd_d": 4.39
    },
    {
      "symbol": "ARMG",
      "name": "Leverage Shares 2X Long ARM Daily ETF",
      "current_price": 30.76,
      "change_pct": -13.62,
      "extra_data": {
        "regular_market_price": 30.76,
        "pre_market_price": 33.0,
        "post_market_price": null,
        "prev_close": 35.61
      },
      "kd_k": 17.31,
      "kd_d": 25.04
    },
    {
      "symbol": "DLLL",
      "name": "GraniteShares 2x Long DELL Daily ETF",
      "current_price": 20.63,
      "change_pct": -15.1,
      "extra_data": {
        "regular_market_price": 20.63,
        "pre_market_price": 21.09,
        "post_market_price": null,
        "prev_close": 24.3
      },
      "kd_k": 9.41,
      "kd_d": 9.91
    },
    {
      "symbol": "QCOM",
      "name": "QUALCOMM Incorporated",
      "current_price": 176.25,
      "change_pct": -3.12,
      "extra_data": {
        "regular_market_price": 176.25,
        "pre_market_price": 179.3,
        "post_market_price": null,
        "prev_close": 181.92
      },
      "kd_k": 9.16,
      "kd_d": 17.23
    },
    {
      "symbol": "QCML",
      "name": "GraniteShares 2x Long QCOM Daily ETF",
      "current_price": 17.93,
      "change_pct": -6.52,
      "extra_data": {
        "regular_market_price": 17.93,
        "pre_market_price": 18.48,
        "post_market_price": null,
        "prev_close": 19.18
      },
      "kd_k": 7.88,
      "kd_d": 15.22
    }
  ],
  "errors": []
}