{
  "timestamp": "2026-05-23T00:25:01.027852",
  "date": "2026-05-23",
  "macro": {
    "us10y": {
      "value": 4.578,
      "change": -0.008
    },
    "dxy": {
      "value": 99.28,
      "change": 0.09
    },
    "fear_greed": {
      "value": 16.59,
      "change": -0.17,
      "label": "VIX Index",
      "timestamp": "2026-05-23T00:24:57.640801"
    },
    "btc": {
      "value": 76761.0,
      "change_pct": -1.0
    }
  },
  "stocks_processed": 96,
  "stocks_successful": 96,
  "stocks_failed": 0,
  "new_alerts": 10,
  "overbought_count": 8,
  "oversold_count": 2,
  "normal_count": 86,
  "overbought_stocks": [
    {
      "symbol": "00915.TW",
      "name": "凱基優選高股息30",
      "current_price": 27.43,
      "change_pct": 0.07,
      "extra_data": {
        "regular_market_price": 27.43,
        "pre_market_price": null,
        "post_market_price": null,
        "prev_close": 27.41
      },
      "kd_k": 83.37,
      "kd_d": 80.01
    },
    {
      "symbol": "00918.TW",
      "name": "大華優利高填息30",
      "current_price": 26.99,
      "change_pct": 1.5,
      "extra_data": {
        "regular_market_price": 26.99,
        "pre_market_price": null,
        "post_market_price": null,
        "prev_close": 26.59
      },
      "kd_k": 89.26,
      "kd_d": 84.87
    },
    {
      "symbol": "00919.TW",
      "name": "群益台灣精選高息",
      "current_price": 26.73,
      "change_pct": 0.75,
      "extra_data": {
        "regular_market_price": 26.73,
        "pre_market_price": null,
        "post_market_price": null,
        "prev_close": 26.53
      },
      "kd_k": 85.31,
      "kd_d": 79.71
    },
    {
      "symbol": "00910.TW",
      "name": "復華航太衛星",
      "current_price": 78.1,
      "change_pct": 1.1,
      "extra_data": {
        "regular_market_price": 78.1,
        "pre_market_price": null,
        "post_market_price": null,
        "prev_close": 77.25
      },
      "kd_k": 93.75,
      "kd_d": 89.42
    },
    {
      "symbol": "AAPL",
      "name": "Apple Inc.",
      "current_price": 310.34,
      "change_pct": 1.75,
      "extra_data": {
        "regular_market_price": 310.34,
        "pre_market_price": null,
        "post_market_price": null,
        "prev_close": 304.99
      },
      "kd_k": 91.06,
      "kd_d": 88.39
    },
    {
      "symbol": "CRWD",
      "name": "CrowdStrike Holdings Inc.",
      "current_price": 671.7,
      "change_pct": 3.62,
      "extra_data": {
        "regular_market_price": 671.7,
        "pre_market_price": null,
        "post_market_price": null,
        "prev_close": 648.23
      },
      "kd_k": 95.55,
      "kd_d": 94.96
    },
    {
      "symbol": "RKLB",
      "name": "Rocket Lab USA, Inc.",
      "current_price": 137.8,
      "change_pct": 9.84,
      "extra_data": {
        "regular_market_price": 137.8,
        "pre_market_price": null,
        "post_market_price": null,
        "prev_close": 125.45
      },
      "kd_k": 83.8,
      "kd_d": 83.27
    },
    {
      "symbol": "RKLX",
      "name": "Defiance Daily Target 2X Long RKLB ETF",
      "current_price": 96.38,
      "change_pct": 19.98,
      "extra_data": {
        "regular_market_price": 96.38,
        "pre_market_price": null,
        "post_market_price": null,
        "prev_close": 80.33
      },
      "kd_k": 81.09,
      "kd_d": 80.02
    }
  ],
  "oversold_stocks": [
    {
      "symbol": "00665L.TW",
      "name": "富邦恒生國企正2",
      "current_price": 9.69,
      "change_pct": 0.31,
      "extra_data": {
        "regular_market_price": 9.69,
        "pre_market_price": null,
        "post_market_price": null,
        "prev_close": 9.66
      },
      "kd_k": 14.41,
      "kd_d": 25.07
    },
    {
      "symbol": "6026.TWO",
      "name": "福邦證",
      "current_price": 15.3,
      "change_pct": -0.33,
      "extra_data": {
        "regular_market_price": 15.3,
        "pre_market_price": null,
        "post_market_price": null,
        "prev_close": 15.35
      },
      "kd_k": 17.84,
      "kd_d": 22.42
    }
  ],
  "errors": []
}