{
  "timestamp": "2026-03-24T16:49:17.182101",
  "date": "2026-03-24",
  "stocks_processed": 64,
  "stocks_successful": 64,
  "stocks_failed": 0,
  "new_alerts": 0,
  "overbought_count": 0,
  "oversold_count": 6,
  "normal_count": 58,
  "overbought_stocks": [],
  "oversold_stocks": [
    {
      "symbol": "2317.TW",
      "name": "鴻海",
      "kd_k": 9.59,
      "kd_d": 15.68
    },
    {
      "symbol": "00635U.TW",
      "name": "期元大S&P黃金",
      "kd_k": 7.33,
      "kd_d": 12.95
    },
    {
      "symbol": "MSFT",
      "name": "Microsoft Corp.",
      "kd_k": 10.38,
      "kd_d": 19.13
    },
    {
      "symbol": "META",
      "name": "Meta Platforms Inc.",
      "kd_k": 16.12,
      "kd_d": 19.96
    },
    {
      "symbol": "MSFU",
      "name": "Direxion Daily MSFT Bull 2X Shares",
      "kd_k": 9.64,
      "kd_d": 18.03
    },
    {
      "symbol": "FBL",
      "name": "GraniteShares 2x Long META Daily ETF",
      "kd_k": 15.18,
      "kd_d": 18.7
    }
  ],
  "errors": []
}