{
  "timestamp": "2026-03-26T16:54:57.628127",
  "date": "2026-03-26",
  "macro": {
    "us10y": {
      "value": 4.328,
      "change": -0.064
    },
    "dxy": {
      "value": 99.7,
      "change": 0.1
    },
    "fear_greed": {
      "value": 27.07,
      "change": 1.74,
      "label": "VIX Index",
      "timestamp": "2026-03-26T16:54:56.977559"
    },
    "btc": {
      "value": 69931.0,
      "change_pct": -1.93
    }
  },
  "stocks_processed": 68,
  "stocks_successful": 68,
  "stocks_failed": 0,
  "new_alerts": 0,
  "overbought_count": 1,
  "oversold_count": 12,
  "normal_count": 55,
  "overbought_stocks": [
    {
      "symbol": "00910.TW",
      "name": "復華航太衛星",
      "current_price": 61.0,
      "change_pct": 4.1,
      "extra_data": {
        "regular_market_price": 61.0,
        "pre_market_price": null,
        "post_market_price": null,
        "prev_close": 58.6
      },
      "kd_k": 81.02,
      "kd_d": 75.52
    }
  ],
  "oversold_stocks": [
    {
      "symbol": "2317.TW",
      "name": "鴻海",
      "current_price": 200.5,
      "change_pct": 0.25,
      "extra_data": {
        "regular_market_price": 200.5,
        "pre_market_price": null,
        "post_market_price": null,
        "prev_close": 200.0
      },
      "kd_k": 19.16,
      "kd_d": 16.67
    },
    {
      "symbol": "2454.TW",
      "name": "聯發科",
      "current_price": 1590.0,
      "change_pct": -1.85,
      "extra_data": {
        "regular_market_price": 1590.0,
        "pre_market_price": null,
        "post_market_price": null,
        "prev_close": 1620.0
      },
      "kd_k": 13.41,
      "kd_d": 23.85
    },
    {
      "symbol": "00757.TW",
      "name": "統一FANG+",
      "current_price": 106.6,
      "change_pct": -0.93,
      "extra_data": {
        "regular_market_price": 106.6,
        "pre_market_price": null,
        "post_market_price": null,
        "prev_close": 107.6
      },
      "kd_k": 17.18,
      "kd_d": 29.24
    },
    {
      "symbol": "00635U.TW",
      "name": "期元大S&P黃金",
      "current_price": 47.56,
      "change_pct": -1.45,
      "extra_data": {
        "regular_market_price": 47.56,
        "pre_market_price": null,
        "post_market_price": null,
        "prev_close": 48.26
      },
      "kd_k": 18.03,
      "kd_d": 15.07
    },
    {
      "symbol": "MSFT",
      "name": "Microsoft Corp.",
      "current_price": 371.04,
      "change_pct": -0.46,
      "extra_data": {
        "regular_market_price": 371.04,
        "pre_market_price": 368.82,
        "post_market_price": null,
        "prev_close": 372.74
      },
      "kd_k": 7.97,
      "kd_d": 15.31
    },
    {
      "symbol": "META",
      "name": "Meta Platforms Inc.",
      "current_price": 594.89,
      "change_pct": 0.33,
      "extra_data": {
        "regular_market_price": 594.89,
        "pre_market_price": 589.51,
        "post_market_price": null,
        "prev_close": 592.92
      },
      "kd_k": 15.06,
      "kd_d": 18.05
    },
    {
      "symbol": "CRWD",
      "name": "CrowdStrike Holdings Inc.",
      "current_price": 385.86,
      "change_pct": -1.81,
      "extra_data": {
        "regular_market_price": 385.86,
        "pre_market_price": 384.15,
        "post_market_price": null,
        "prev_close": 392.99
      },
      "kd_k": 16.35,
      "kd_d": 32.11
    },
    {
      "symbol": "MSFU",
      "name": "Direxion Daily MSFT Bull 2X Shares",
      "current_price": 23.2,
      "change_pct": -0.94,
      "extra_data": {
        "regular_market_price": 23.2,
        "pre_market_price": 22.91,
        "post_market_price": null,
        "prev_close": 23.42
      },
      "kd_k": 7.36,
      "kd_d": 14.4
    },
    {
      "symbol": "FBL",
      "name": "GraniteShares 2x Long META Daily ETF",
      "current_price": 25.1806,
      "change_pct": 0.48,
      "extra_data": {
        "regular_market_price": 25.1806,
        "pre_market_price": 24.76,
        "post_market_price": null,
        "prev_close": 25.06
      },
      "kd_k": 13.67,
      "kd_d": 16.7
    },
    {
      "symbol": "NFXL",
      "name": "Direxion Daily NFLX Bull 2X Shares",
      "current_price": 27.8252,
      "change_pct": 3.25,
      "extra_data": {
        "regular_market_price": 27.8252,
        "pre_market_price": 27.7,
        "post_market_price": null,
        "prev_close": 26.95
      },
      "kd_k": 18.76,
      "kd_d": 20.81
    },
    {
      "symbol": "FNGS",
      "name": "MicroSectors FANG+ Index ETN",
      "current_price": 61.02,
      "change_pct": 0.35,
      "extra_data": {
        "regular_market_price": 61.02,
        "pre_market_price": null,
        "post_market_price": null,
        "prev_close": 60.81
      },
      "kd_k": 14.26,
      "kd_d": 22.66
    },
    {
      "symbol": "FNGG",
      "name": "Direxion Daily NYSE FANG+ Bull 2X Shares",
      "current_price": 161.47,
      "change_pct": 0.65,
      "extra_data": {
        "regular_market_price": 161.47,
        "pre_market_price": 160.0,
        "post_market_price": null,
        "prev_close": 160.42
      },
      "kd_k": 11.51,
      "kd_d": 19.62
    }
  ],
  "errors": []
}